markyp_bootstrap4/__init__.py
markyp_bootstrap4/alerts.py
markyp_bootstrap4/badges.py
markyp_bootstrap4/breadcrumbs.py
markyp_bootstrap4/button_groups.py
markyp_bootstrap4/buttons.py
markyp_bootstrap4/cards.py
markyp_bootstrap4/carousels.py
markyp_bootstrap4/collapses.py
markyp_bootstrap4/colors.py
markyp_bootstrap4/dropdowns.py
markyp_bootstrap4/elements.py
markyp_bootstrap4/forms.py
markyp_bootstrap4/input_groups.py
markyp_bootstrap4/jumbotrons.py
markyp_bootstrap4/layout.py
markyp_bootstrap4/list_groups.py
markyp_bootstrap4/modals.py
markyp_bootstrap4/navbars.py
markyp_bootstrap4/navs.py
markyp_bootstrap4/pagination.py
markyp_bootstrap4/popovers.py
markyp_bootstrap4/progress.py
markyp_bootstrap4/scrollspy.py
markyp_bootstrap4/tabs.py
markyp_bootstrap4/tooltips.py
markyp_bootstrap4-0.2210.1.dist-info/LICENSE
markyp_bootstrap4-0.2210.1.dist-info/METADATA
markyp_bootstrap4-0.2210.1.dist-info/WHEEL
markyp_bootstrap4-0.2210.1.dist-info/top_level.txt
markyp_bootstrap4-0.2210.1.dist-info/RECORD
